orm/__init__.py
orm/table.py
orm/table_relation.py
orm_mysql-1.0.6.dist-info/LICENSE
orm_mysql-1.0.6.dist-info/METADATA
orm_mysql-1.0.6.dist-info/WHEEL
orm_mysql-1.0.6.dist-info/top_level.txt
orm_mysql-1.0.6.dist-info/RECORD
