Metadata-Version: 2.1
Name: orm-mysql
Version: 1.0.6
Summary: An ORM for MySql.
Home-page: https://github.com/hrushikeshj/mysql-orm
Author: Hrushikesh J
Author-email: hrushi2002j@gmail.com
License: MIT
Platform: UNKNOWN
Classifier: License :: OSI Approved :: MIT License
Classifier: Programming Language :: Python :: 3
Classifier: Programming Language :: Python :: 3.7
Requires-Dist: mysql-connector-python
Requires-Dist: pyyaml
